[
  {
    "date": "01-04-2026",
    "subh": "5:07 AM",
    "duhr": "12:32 PM",
    "asar": "4:51 PM",
    "maghrib": "6:39 PM",
    "isha": "7:57 PM",
    "sunrise": "6:22 AM"
  },
  {
    "date": "02-04-2026",
    "subh": "5:07 AM",
    "duhr": "12:32 PM",
    "asar": "4:51 PM",
    "maghrib": "6:39 PM",
    "isha": "7:57 PM",
    "sunrise": "6:22 AM"
  },
  {
    "date": "03-04-2026",
    "subh": "5:07 AM",
    "duhr": "12:32 PM",
    "asar": "4:51 PM",
    "maghrib": "6:39 PM",
    "isha": "7:57 PM",
    "sunrise": "6:22 AM"
  },
  {
    "date": "04-04-2026",
    "subh": "5:05 AM",
    "duhr": "12:31 PM",
    "asar": "4:50 PM",
    "maghrib": "6:39 PM",
    "isha": "7:57 PM",
    "sunrise": "6:20 AM"
  },
  {
    "date": "05-04-2026",
    "subh": "5:05 AM",
    "duhr": "12:31 PM",
    "asar": "4:50 PM",
    "maghrib": "6:39 PM",
    "isha": "7:57 PM",
    "sunrise": "6:20 AM"
  },
  {
    "date": "06-04-2026",
    "subh": "5:05 AM",
    "duhr": "12:31 PM",
    "asar": "4:50 PM",
    "maghrib": "6:39 PM",
    "isha": "7:57 PM",
    "sunrise": "6:20 AM"
  },
  {
    "date": "07-04-2026",
    "subh": "5:03 AM",
    "duhr": "12:30 PM",
    "asar": "4:49 PM",
    "maghrib": "6:39 PM",
    "isha": "7:57 PM",
    "sunrise": "6:18 AM"
  },
  {
    "date": "08-04-2026",
    "subh": "5:03 AM",
    "duhr": "12:30 PM",
    "asar": "4:49 PM",
    "maghrib": "6:39 PM",
    "isha": "7:57 PM",
    "sunrise": "6:18 AM"
  },
  {
    "date": "09-04-2026",
    "subh": "5:03 AM",
    "duhr": "12:30 PM",
    "asar": "4:49 PM",
    "maghrib": "6:39 PM",
    "isha": "7:57 PM",
    "sunrise": "6:18 AM"
  },
  {
    "date": "10-04-2026",
    "subh": "5:01 AM",
    "duhr": "12:29 PM",
    "asar": "4:48 PM",
    "maghrib": "6:39 PM",
    "isha": "7:57 PM",
    "sunrise": "6:17 AM"
  },
  {
    "date": "11-04-2026",
    "subh": "5:01 AM",
    "duhr": "12:29 PM",
    "asar": "4:48 PM",
    "maghrib": "6:39 PM",
    "isha": "7:57 PM",
    "sunrise": "6:17 AM"
  },
  {
    "date": "12-04-2026",
    "subh": "5:01 AM",
    "duhr": "12:29 PM",
    "asar": "4:48 PM",
    "maghrib": "6:39 PM",
    "isha": "7:57 PM",
    "sunrise": "6:17 AM"
  },
  {
    "date": "13-04-2026",
    "subh": "5:00 AM",
    "duhr": "12:29 PM",
    "asar": "4:47 PM",
    "maghrib": "6:39 PM",
    "isha": "7:58 PM",
    "sunrise": "6:16 AM"
  },
  {
    "date": "14-04-2026",
    "subh": "5:00 AM",
    "duhr": "12:29 PM",
    "asar": "4:47 PM",
    "maghrib": "6:39 PM",
    "isha": "7:58 PM",
    "sunrise": "6:16 AM"
  },
  {
    "date": "15-04-2026",
    "subh": "5:00 AM",
    "duhr": "12:29 PM",
    "asar": "4:47 PM",
    "maghrib": "6:39 PM",
    "isha": "7:58 PM",
    "sunrise": "6:16 AM"
  },
  {
    "date": "16-04-2026",
    "subh": "4:58 AM",
    "duhr": "12:28 PM",
    "asar": "4:46 PM",
    "maghrib": "6:39 PM",
    "isha": "7:58 PM",
    "sunrise": "6:14 AM"
  },
  {
    "date": "17-04-2026",
    "subh": "4:58 AM",
    "duhr": "12:28 PM",
    "asar": "4:46 PM",
    "maghrib": "6:39 PM",
    "isha": "7:58 PM",
    "sunrise": "6:14 AM"
  },
  {
    "date": "18-04-2026",
    "subh": "4:58 AM",
    "duhr": "12:28 PM",
    "asar": "4:46 PM",
    "maghrib": "6:39 PM",
    "isha": "7:58 PM",
    "sunrise": "6:14 AM"
  },
  {
    "date": "19-04-2026",
    "subh": "4:56 AM",
    "duhr": "12:27 PM",
    "asar": "4:46 PM",
    "maghrib": "6:39 PM",
    "isha": "7:58 PM",
    "sunrise": "6:13 AM"
  },
  {
    "date": "20-04-2026",
    "subh": "4:56 AM",
    "duhr": "12:27 PM",
    "asar": "4:46 PM",
    "maghrib": "6:39 PM",
    "isha": "7:58 PM",
    "sunrise": "6:13 AM"
  },
  {
    "date": "21-04-2026",
    "subh": "4:56 AM",
    "duhr": "12:27 PM",
    "asar": "4:46 PM",
    "maghrib": "6:39 PM",
    "isha": "7:58 PM",
    "sunrise": "6:13 AM"
  },
  {
    "date": "22-04-2026",
    "subh": "4:55 AM",
    "duhr": "12:27 PM",
    "asar": "4:47 PM",
    "maghrib": "6:40 PM",
    "isha": "7:59 PM",
    "sunrise": "6:12 AM"
  },
  {
    "date": "23-04-2026",
    "subh": "4:55 AM",
    "duhr": "12:27 PM",
    "asar": "4:47 PM",
    "maghrib": "6:40 PM",
    "isha": "7:59 PM",
    "sunrise": "6:12 AM"
  },
  {
    "date": "24-04-2026",
    "subh": "4:55 AM",
    "duhr": "12:27 PM",
    "asar": "4:47 PM",
    "maghrib": "6:40 PM",
    "isha": "7:59 PM",
    "sunrise": "6:12 AM"
  },
  {
    "date": "25-04-2026",
    "subh": "4:53 AM",
    "duhr": "12:26 PM",
    "asar": "4:47 PM",
    "maghrib": "6:40 PM",
    "isha": "7:59 PM",
    "sunrise": "6:10 AM"
  },
  {
    "date": "26-04-2026",
    "subh": "4:53 AM",
    "duhr": "12:26 PM",
    "asar": "4:47 PM",
    "maghrib": "6:40 PM",
    "isha": "7:59 PM",
    "sunrise": "6:10 AM"
  },
  {
    "date": "27-04-2026",
    "subh": "4:53 AM",
    "duhr": "12:26 PM",
    "asar": "4:47 PM",
    "maghrib": "6:40 PM",
    "isha": "7:59 PM",
    "sunrise": "6:10 AM"
  },
  {
    "date": "28-04-2026",
    "subh": "4:51 AM",
    "duhr": "12:25 PM",
    "asar": "4:47 PM",
    "maghrib": "6:40 PM",
    "isha": "8:00 PM",
    "sunrise": "6:08 AM"
  },
  {
    "date": "29-04-2026",
    "subh": "4:51 AM",
    "duhr": "12:25 PM",
    "asar": "4:47 PM",
    "maghrib": "6:40 PM",
    "isha": "8:00 PM",
    "sunrise": "6:08 AM"
  },
  {
    "date": "30-04-2026",
    "subh": "4:51 AM",
    "duhr": "12:25 PM",
    "asar": "4:47 PM",
    "maghrib": "6:40 PM",
    "isha": "8:00 PM",
    "sunrise": "6:08 AM"
  }
]